hzfile/__init__.py
hzfile/__utils__.py
hzfile-0.1.0.dist-info/LICENSE
hzfile-0.1.0.dist-info/METADATA
hzfile-0.1.0.dist-info/WHEEL
hzfile-0.1.0.dist-info/top_level.txt
hzfile-0.1.0.dist-info/RECORD
