Metadata-Version: 2.1
Name: hzfile
Version: 0.1.0
Summary: 一个用于学习的模块，用于自定义的'.hz'格式文件的生成和读取。
Home-page: https://github.com/hrpzcf/hzfile
Author: hrpzcf
Author-email: hrpzcf@foxmail.com
Maintainer: hrpzcf
Maintainer-email: hrpzcf@foxmail.com
License: MIT License
Keywords: hz,.hz,hz file
Platform: UNKNOWN
Classifier: Intended Audience :: Developers
Classifier: Development Status :: 4 - Beta
Classifier: License :: OSI Approved :: MIT License
Classifier: Programming Language :: Python :: 3.5
Classifier: Programming Language :: Python :: 3.6
Classifier: Programming Language :: Python :: 3.7
Classifier: Programming Language :: Python :: 3.8
Classifier: Programming Language :: Python :: 3.9
Classifier: Programming Language :: Python :: 3.10
Requires-Python: >=3.5
